<input>
    <include> ../baseline_mesh.xml </include>

    <abaqus>
        <E> 71000 </E>
        <nu> 0.33 </nu>
        <displacement_yy> 0.01 </displacement_yy>
        <plastic_stresses> 350, 470, 710, 710 </plastic_stresses>
    </abaqus>

    <settings>
        <verbose> True </verbose>
        <restart> False </restart>
        <mesh_min_angle> 25 </mesh_min_angle>
        <mesh_max_edge_length> 0.00175 </mesh_max_edge_length>

        <rng_seeds>
            <size> 667 </size>
        </rng_seeds>

    </settings>
</input>